oogway/__init__.py
oogway/address.py
oogway/convert.py
oogway/exceptions.py
oogway/external.py
oogway/fees.py
oogway/key.py
oogway/net.py
oogway/operation.py
oogway/request.py
oogway/rpc.py
oogway/transaction.py
oogway/tx.py
oogway/validate.py
oogway/cli/__init__.py
oogway/cli/cli.py
oogway/cli/cli_address.py
oogway/cli/cli_balance.py
oogway/cli/cli_broadcast.py
oogway/cli/cli_convert.py
oogway/cli/cli_fees.py
oogway/cli/cli_request.py
oogway/seed/__init__.py
oogway/seed/base58.py
oogway/seed/gen.py
oogway/seed/wordlist/__init__.py
oogway/seed/wordlist/english.txt
oogway/utils/__init__.py
oogway/utils/base58.py
oogway/utils/bech32.py
oogway/utils/constants.py
oogway/utils/crypto.py
oogway/utils/curve.py
oogway/utils/format.py
oogway/utils/meta.py
oogway/utils/opcodes.py
oogway/utils/utils.py
tests/__init__.py
tests/data.py
tests/test_convert.py
tests/test_fees.py
tests/test_imports.py
tests/test_key.py
tests/test_mnemonic.py
tests/test_operation.py
tests/test_request_payment.py
tests/test_validate.py
oogway-0.7.1.dist-info/AUTHORS.md
oogway-0.7.1.dist-info/LICENSE
oogway-0.7.1.dist-info/METADATA
oogway-0.7.1.dist-info/WHEEL
oogway-0.7.1.dist-info/entry_points.txt
oogway-0.7.1.dist-info/top_level.txt
oogway-0.7.1.dist-info/RECORD
