Metadata-Version: 2.1
Name: oogway
Version: 0.7.1
Summary: A simple, yet secure Bitcoin utility library
Home-page: https://github.com/merwane/oogway
Author: Merwane Drai
Author-email: merwane@6conf.com
License: MIT
Download-URL: https://github.com/merwane/oogway
Keywords: bitcoin-wallet,bitcoin,bitcoin-sdk,bitcoin-cli
Platform: UNKNOWN
Classifier: Intended Audience :: Developers
Classifier: License :: OSI Approved :: MIT License
Classifier: Natural Language :: English
Classifier: Operating System :: OS Independent
Classifier: Programming Language :: Python :: 3.6
Classifier: Programming Language :: Python :: 3.7
Classifier: Programming Language :: Python :: 3.8
Requires-Dist: ecdsa
Requires-Dist: Click
Requires-Dist: requests
Requires-Dist: coincurve
